wdcuration/__init__.py
wdcuration/api_searches.py
wdcuration/dict_handler.py
wdcuration/quickstatements.py
wdcuration/sheet_based_curation.py
wdcuration/sparql.py
wdcuration/utils.py
wdcuration-0.2.1.dist-info/LICENSE
wdcuration-0.2.1.dist-info/METADATA
wdcuration-0.2.1.dist-info/WHEEL
wdcuration-0.2.1.dist-info/top_level.txt
wdcuration-0.2.1.dist-info/RECORD
