Metadata-Version: 2.1
Name: wdcuration
Version: 0.2.1
Summary: Utils for curating unstructured data into Wikidata
Home-page: https://github.com/lubianat/wdcuration
Author: Tiago Lubiana
Author-email: tiago.lubiana.alves@usp.br
License: MIT license
Keywords: wdcuration
Classifier: Development Status :: 2 - Pre-Alpha
Classifier: Intended Audience :: Developers
Classifier: License :: OSI Approved :: MIT License
Classifier: Natural Language :: English
Classifier: Programming Language :: Python :: 3
Classifier: Programming Language :: Python :: 3.7
Classifier: Programming Language :: Python :: 3.8
Classifier: Programming Language :: Python :: 3.9
Classifier: Programming Language :: Python :: 3.10
Requires-Python: >=3.6
License-File: LICENSE
Requires-Dist: requests
Requires-Dist: SPARQLWrapper
Requires-Dist: tqdm
Requires-Dist: inflect
Requires-Dist: pandas
Requires-Dist: aiohttp
Provides-Extra: docs
Requires-Dist: mkdocs ; extra == 'docs'
Requires-Dist: mkdocstrings ; extra == 'docs'
Requires-Dist: mkdocstrings.python ; extra == 'docs'
Provides-Extra: tests
Requires-Dist: pytest ; extra == 'tests'
